sftocsv/__init__.py
sftocsv/sftocsv.py
sftocsv/utils.py
sftocsv-1.0.3.dist-info/LICENSE
sftocsv-1.0.3.dist-info/METADATA
sftocsv-1.0.3.dist-info/WHEEL
sftocsv-1.0.3.dist-info/top_level.txt
sftocsv-1.0.3.dist-info/RECORD
