Metadata-Version: 2.1
Name: sftocsv
Version: 1.0.3
Summary: Salesforce queries made easy
Author-email: Phillip Harry T <philliptinsley44@gmail.com>
License: Apache NON-AI License, Version 2.0
Keywords: Salesforce,SF,saleforce,SQL,SOQL,sql,soql,query,query language,csv,CSV,REST API,Rest,connected app
Classifier: License :: Other/Proprietary License
Classifier: Programming Language :: Python
Classifier: Programming Language :: Python :: 3
Classifier: Intended Audience :: Information Technology
Requires-Python: >=3.8
License-File: LICENSE
